[
   {
      "lessonNo" : 114,
      "chinese" : "你知道,",
      "sentenceNo" : 1,
      "courseNo" : 2,
      "timeline" : "00:00:06,670 --> 00:00:07,779",
      "english" : "I started out, you know,"
   },
   {
      "lessonNo" : 114,
      "chinese" : "作为California的一个年轻人,",
      "sentenceNo" : 2,
      "courseNo" : 2,
      "timeline" : "00:00:08,029 --> 00:00:09,800",
      "english" : "as a young man in California going to,"
   },
   {
      "lessonNo" : 114,
      "chinese" : "我从小在当地关于California一个小镇的历史博物馆长大.",
      "sentenceNo" : 3,
      "courseNo" : 2,
      "timeline" : "00:00:10,503 --> 00:00:15,418",
      "english" : "I guess, local history museums about the history of the little town in California that I was raised in."
   },
   {
      "lessonNo" : 114,
      "chinese" : "我一直很喜欢那些博物馆",
      "sentenceNo" : 4,
      "courseNo" : 2,
      "timeline" : "00:00:15,675 --> 00:00:16,602",
      "english" : "I always liked them."
   },
   {
      "lessonNo" : 114,
      "chinese" : "Oh, 我这辈子常去博物馆.",
      "sentenceNo" : 5,
      "courseNo" : 2,
      "timeline" : "00:00:16,713 --> 00:00:18,615",
      "english" : "Oh, I've been going to museums all my life."
   },
   {
      "lessonNo" : 114,
      "chinese" : "我从小就习惯做那些事了, 你知道吗,",
      "sentenceNo" : 6,
      "courseNo" : 2,
      "timeline" : "00:00:18,721 --> 00:00:22,238",
      "english" : "I was brought up to do those kinds of things, you know,"
   },
   {
      "lessonNo" : 114,
      "chinese" : "在家听歌剧, 去博物馆,",
      "sentenceNo" : 7,
      "courseNo" : 2,
      "timeline" : "00:00:22,263 --> 00:00:24,283",
      "english" : "listen to opera at home, go to museums,"
   },
   {
      "lessonNo" : 114,
      "chinese" : "这都是我成长的一部分.",
      "sentenceNo" : 8,
      "courseNo" : 2,
      "timeline" : "00:00:24,322 --> 00:00:25,613",
      "english" : "it was all part of my upbringing."
   },
   {
      "lessonNo" : 114,
      "chinese" : "我认为这是脱离日常生活的某种休憩,",
      "sentenceNo" : 9,
      "courseNo" : 2,
      "timeline" : "00:00:25,631 --> 00:00:28,242",
      "english" : "I think it's just a break from the every day,"
   },
   {
      "lessonNo" : 114,
      "chinese" : "让人摆脱每时每刻都在你眼前晃来晃去的喧闹的街道和人群;",
      "sentenceNo" : 10,
      "courseNo" : 2,
      "timeline" : "00:00:28,309 --> 00:00:32,864",
      "english" : "the madness of the streets and people in your face all the time;"
   },
   {
      "lessonNo" : 114,
      "chinese" : "那里非常安静,",
      "sentenceNo" : 11,
      "courseNo" : 2,
      "timeline" : "00:00:32,894 --> 00:00:34,149",
      "english" : "and it's very quiet in there,"
   },
   {
      "lessonNo" : 114,
      "chinese" : "使人能花点儿时间想想日常琐事以外的事情.",
      "sentenceNo" : 12,
      "courseNo" : 2,
      "timeline" : "00:00:34,672 --> 00:00:38,492",
      "english" : "and taking a little time to think about things other than the daily routine."
   },
   {
      "lessonNo" : 114,
      "chinese" : "我参观各式各样的博物馆.",
      "sentenceNo" : 13,
      "courseNo" : 2,
      "timeline" : "00:00:38,766 --> 00:00:40,918",
      "english" : "I go to all kinds of museums."
   },
   {
      "lessonNo" : 114,
      "chinese" : "我定期去艺术博物馆,",
      "sentenceNo" : 14,
      "courseNo" : 2,
      "timeline" : "00:00:40,926 --> 00:00:43,885",
      "english" : "I go to the museum of fine arts regularly,"
   },
   {
      "lessonNo" : 114,
      "chinese" : "也去简朴的小博物馆",
      "sentenceNo" : 15,
      "courseNo" : 2,
      "timeline" : "00:00:44,313 --> 00:00:47,443",
      "english" : "and I go to like to go to the small, funky museums"
   },
   {
      "lessonNo" : 114,
      "chinese" : "而且我喜欢去看特别的展览而且我总是去.",
      "sentenceNo" : 16,
      "courseNo" : 2,
      "timeline" : "00:00:47,547 --> 00:00:52,423",
      "english" : "and I like to go and see special exhibits and I go all the time."
   },
   {
      "lessonNo" : 114,
      "chinese" : "你去看,",
      "sentenceNo" : 17,
      "courseNo" : 2,
      "timeline" : "00:00:52,496 --> 00:00:53,110",
      "english" : "You go to see,"
   },
   {
      "lessonNo" : 114,
      "chinese" : "er,人们表达自己的不同方式,",
      "sentenceNo" : 18,
      "courseNo" : 2,
      "timeline" : "00:00:53,261 --> 00:00:55,874",
      "english" : "er, different ways people express themselves,"
   },
   {
      "lessonNo" : 114,
      "chinese" : "无论是雕塑, 民间艺术, 或是科学, 或是, um, 你知道的, 绘画, 或者, 或者, 诸如此类的东西.",
      "sentenceNo" : 19,
      "courseNo" : 2,
      "timeline" : "00:00:55,990 --> 00:01:02,980",
      "english" : "whether it's sculpture, folk art, or science, or, um, you know, fine art painting, or, or, whatever."
   },
   {
      "lessonNo" : 114,
      "chinese" : "我觉得观看过去的人类和文明的伟大成就使我多少感受到作为人类意味着什么.",
      "sentenceNo" : 20,
      "courseNo" : 2,
      "timeline" : "00:01:03,049 --> 00:01:11,276",
      "english" : "It gets me in touch a little bit with I think what it means to be human, by looking at great achievements of past humans and human civilizations,"
   },
   {
      "lessonNo" : 114,
      "chinese" : "这是我非常喜欢的.",
      "sentenceNo" : 21,
      "courseNo" : 2,
      "timeline" : "00:01:11,348 --> 00:01:13,635",
      "english" : "which I enjoy a lot,"
   },
   {
      "lessonNo" : 114,
      "chinese" : "我常常想它展示了某种值得追求的东西，",
      "sentenceNo" : 22,
      "courseNo" : 2,
      "timeline" : "00:01:13,673 --> 00:01:17,019",
      "english" : "it shows things to aspire towards I think often times and something to,"
   },
   {
      "lessonNo" : 114,
      "chinese" : "我想如果我们理解了这些东西,",
      "sentenceNo" : 23,
      "courseNo" : 2,
      "timeline" : "00:01:17,028 --> 00:01:18,334",
      "english" : "I think if we understand these things,"
   },
   {
      "lessonNo" : 114,
      "chinese" : "我们就能更好地理解现实.",
      "sentenceNo" : 24,
      "courseNo" : 2,
      "timeline" : "00:01:18,373 --> 00:01:20,820",
      "english" : "we can understand the present a lot better."
   },
   {
      "lessonNo" : 114,
      "chinese" : "在博物馆里, 我比在世界上任何我能想到的地方都更快乐.",
      "sentenceNo" : 25,
      "courseNo" : 2,
      "timeline" : "00:01:20,855 --> 00:01:24,957",
      "english" : "I'm happier when I'm in a museum than any place in the world that I can think of."
   },
   {
      "lessonNo" : 114,
      "chinese" : "但这对于我也像是在读一本书",
      "sentenceNo" : 26,
      "courseNo" : 2,
      "timeline" : "00:01:25,124 --> 00:01:26,694",
      "english" : "But it's also like reading a book for me"
   },
   {
      "lessonNo" : 114,
      "chinese" : "我想这是一条了解新信息的捷径.",
      "sentenceNo" : 27,
      "courseNo" : 2,
      "timeline" : "00:01:26,700 --> 00:01:29,840",
      "english" : "I guess it's a quick way to learn new information."
   }
]
