[
   {
      "lessonNo" : "04--2",
      "sentenceNo" : 1,
      "english" : "OK, Richard. That's terrific."
   },
   {
      "lessonNo" : "04--2",
      "sentenceNo" : 2,
      "english" : "Your pressure is 120 over 75, and that's fine."
   },
   {
      "lessonNo" : "04--2",
      "sentenceNo" : 3,
      "english" : "Now stand up, please."
   },
   {
      "lessonNo" : "04--2",
      "sentenceNo" : 4,
      "english" : "Good, it's 122 over 80."
   },
   {
      "lessonNo" : "04--2",
      "sentenceNo" : 5,
      "english" : "You can sit down now."
   },
   {
      "lessonNo" : "04--2",
      "sentenceNo" : 6,
      "english" : "When was your last complete physical?"
   },
   {
      "lessonNo" : "04--2",
      "sentenceNo" : 7,
      "english" : "Six months ago."
   },
   {
      "lessonNo" : "04--2",
      "sentenceNo" : 8,
      "english" : "Good. Do you have any back or knee problems?"
   },
   {
      "lessonNo" : "04--2",
      "sentenceNo" : 9,
      "english" : "Nope. I am in perfect health."
   },
   {
      "lessonNo" : "04--2",
      "sentenceNo" : 10,
      "english" : "What do you do for a living, Mr. Stewart?"
   },
   {
      "lessonNo" : "04--2",
      "sentenceNo" : 11,
      "english" : "I'm a photographer."
   },
   {
      "lessonNo" : "04--2",
      "sentenceNo" : 12,
      "english" : "Interesting. What do you photograph?"
   },
   {
      "lessonNo" : "04--2",
      "sentenceNo" : 13,
      "english" : "Everything. The American scene. People, places, events."
   },
   {
      "lessonNo" : "04--2",
      "sentenceNo" : 14,
      "english" : "Did you ever think of photographing an aerobics class?"
   },
   {
      "lessonNo" : "04--2",
      "sentenceNo" : 15,
      "english" : "No...I can't remember taking pictures of people exercising."
   },
   {
      "lessonNo" : "04--2",
      "sentenceNo" : 16,
      "english" : "But don't you think it'd be a good subject?"
   },
   {
      "lessonNo" : "04--2",
      "sentenceNo" : 17,
      "english" : "Sure."
   },
   {
      "lessonNo" : "04--2",
      "sentenceNo" : 18,
      "english" : "I need some good photos for my advertising, Mr. Stewart."
   },
   {
      "lessonNo" : "04--2",
      "sentenceNo" : 19,
      "english" : "Maybe you can photogragh a class,"
   },
   {
      "lessonNo" : "04--2",
      "sentenceNo" : 20,
      "english" : "and I can give you and Mrs. Stewart"
   },
   {
      "lessonNo" : "04--2",
      "sentenceNo" : 21,
      "english" : "a month of classes free."
   },
   {
      "lessonNo" : "04--2",
      "sentenceNo" : 22,
      "english" : "When can I photograph a class?"
   },
   {
      "lessonNo" : "04--2",
      "sentenceNo" : 23,
      "english" : "Anytime."
   },
   {
      "lessonNo" : "04--2",
      "sentenceNo" : 24,
      "english" : "How about today?"
   },
   {
      "lessonNo" : "04--2",
      "sentenceNo" : 25,
      "english" : "Terrific!"
   },
   {
      "lessonNo" : "04--2",
      "sentenceNo" : 26,
      "english" : "Hi."
   },
   {
      "lessonNo" : "04--2",
      "sentenceNo" : 27,
      "english" : "Oh, hi."
   },
   {
      "lessonNo" : "04--2",
      "sentenceNo" : 28,
      "english" : "Are we ready to go?"
   },
   {
      "lessonNo" : "04--2",
      "sentenceNo" : 29,
      "english" : "Yeah. Yeah. Let's get in our lines."
   },
   {
      "lessonNo" : "04--2",
      "sentenceNo" : 30,
      "english" : "We're going to take it slow first."
   },
   {
      "lessonNo" : "04--2",
      "sentenceNo" : 31,
      "english" : "Stretch up...and we're going to go left first ..."
   },
   {
      "lessonNo" : "04--2",
      "sentenceNo" : 32,
      "english" : "2,3,4 ... now switch. ..."
   },
   {
      "lessonNo" : "04--2",
      "sentenceNo" : 33,
      "english" : "OK, hold to the right."
   },
   {
      "lessonNo" : "04--2",
      "sentenceNo" : 34,
      "english" : "Sunrises. Stretch it out. Flat back."
   },
   {
      "lessonNo" : "04--2",
      "sentenceNo" : 35,
      "english" : "Bring it up...and twists...and side...2 3..."
   },
   {
      "lessonNo" : "04--2",
      "sentenceNo" : 36,
      "english" : "and left...push...push...turn...hit the floor."
   },
   {
      "lessonNo" : "04--2",
      "sentenceNo" : 37,
      "english" : "Take it side again....OK, and switch. Stretch it out."
   },
   {
      "lessonNo" : "04--2",
      "sentenceNo" : 38,
      "english" : "And we're going to warm down with a tango."
   },
   {
      "lessonNo" : "04--2",
      "sentenceNo" : 39,
      "english" : "Left, right. Enjoy it."
   },
   {
      "lessonNo" : "04--2",
      "sentenceNo" : 40,
      "english" : "Richard,"
   },
   {
      "lessonNo" : "04--2",
      "sentenceNo" : 41,
      "english" : "did you go to the Davis Aerobics class today?"
   },
   {
      "lessonNo" : "04--2",
      "sentenceNo" : 42,
      "english" : "Yes, I went to the aerobics class today."
   },
   {
      "lessonNo" : "04--2",
      "sentenceNo" : 43,
      "english" : "What is wrong with you?"
   },
   {
      "lessonNo" : "04--2",
      "sentenceNo" : 44,
      "english" : "Nothing. I am in excellent health."
   },
   {
      "lessonNo" : "04--2",
      "sentenceNo" : 45,
      "english" : "I have ideal blood pressure. A perfect heart."
   },
   {
      "lessonNo" : "04--2",
      "sentenceNo" : 46,
      "english" : "In other words, I'm in wonderful condition."
   },
   {
      "lessonNo" : "04--2",
      "sentenceNo" : 47,
      "english" : "Richard, did you go to the aerobics class, really?"
   },
   {
      "lessonNo" : "04--2",
      "sentenceNo" : 48,
      "english" : "And don't forget to invite Susan for dinner."
   },
   {
      "lessonNo" : "04--2",
      "sentenceNo" : 49,
      "english" : "And your legs don't hurt?"
   },
   {
      "lessonNo" : "04--2",
      "sentenceNo" : 50,
      "english" : "Hurt? What do you mean?"
   },
   {
      "lessonNo" : "04--2",
      "sentenceNo" : 51,
      "english" : "What about your arms? Lift your arms up like this."
   },
   {
      "lessonNo" : "04--2",
      "sentenceNo" : 52,
      "english" : "And they don't hurt not even a little?"
   },
   {
      "lessonNo" : "04--2",
      "sentenceNo" : 53,
      "english" : "Nope."
   },
   {
      "lessonNo" : "04--2",
      "sentenceNo" : 54,
      "english" : "You are in great condition. I can't believe it!"
   }
]
